ncellapi/__init__.py
ncellapi/exceptions.py
ncellapi/models/__init__.py
ncellapi/models/balance.py
ncellapi/models/credentials.py
ncellapi/models/login.py
ncellapi/models/ncell.py
ncellapi/models/sms_model.py
ncellapi/models/usage_detail.py
ncellapi/ncell.py
ncellapi/ncell_api.py
ncellapi/signcode.py
ncellapi-0.2.1.dist-info/LICENSE
ncellapi-0.2.1.dist-info/METADATA
ncellapi-0.2.1.dist-info/WHEEL
ncellapi-0.2.1.dist-info/RECORD
